claude2openai/__init__.py
claude2openai/version.py
claude2openai/api_resources/__init__.py
claude2openai/api_resources/chat_completion.py
claude2openai/tests/test_usage.py
claude2openai-0.0.1.dist-info/LICENSE
claude2openai-0.0.1.dist-info/METADATA
claude2openai-0.0.1.dist-info/WHEEL
claude2openai-0.0.1.dist-info/top_level.txt
claude2openai-0.0.1.dist-info/zip-safe
claude2openai-0.0.1.dist-info/RECORD
