Metadata-Version: 2.1
Name: claude2openai
Version: 0.0.1
Summary: use claude like openai
Home-page: https://github.com/ChuxiJ/claude2openai
Author: ChuxiJ
Author-email: junmingong@gmail.com
Classifier: Programming Language :: Python :: 3
Classifier: License :: OSI Approved :: MIT License
Classifier: Operating System :: OS Independent
Requires-Python: >=3.7.1
License-File: LICENSE
Requires-Dist: requests (>=2.20)
Requires-Dist: slack-sdk
Requires-Dist: aiohttp
Requires-Dist: typing-extensions ; python_version < "3.8"
